
{
  "ConfiguredPortals": [
    {
      "isFlat": true,
      "frameBlock": "kubejs:end_frame_bricks",
      "isFluidIgniter": false,
      "itemIgniter": "kubejs:end_key",
      "dimension": "minecraft:the_end",
      "r": 166,
      "g": 108,
      "b": 149
    },
    {
      "isFlat": false,
      "frameBlock": "kubejs:nether_frame_bricks",
      "isFluidIgniter": false,
      "itemIgniter": "kubejs:nether_key",
      "dimension": "minecraft:the_nether",
      "r": 223,
      "g": 127,
      "b": 40
    },
    {
      "isFlat": false,
      "frameBlock": "kubejs:mining_frame_bricks",
      "isFluidIgniter": false,
      "itemIgniter": "kubejs:mining_key",
      "dimension": "jamd:mining",
      "r": 108,
      "g": 162,
      "b": 166
    },
    {
      "isFlat": false,
      "frameBlock": "kubejs:nether_mining_frame_bricks",
      "isFluidIgniter": false,
      "itemIgniter": "kubejs:nether_mining_key",
      "dimension": "jamd:nether",
      "r": 77,
      "g": 73,
      "b": 77
    },
    {
      "isFlat": false,
      "frameBlock": "kubejs:end_mining_frame_bricks",
      "isFluidIgniter": false,
      "itemIgniter": "kubejs:end_mining_key",
      "dimension": "jamd:end",
      "r": 232,
      "g": 244,
      "b": 178
    },
    {
      "isFlat": false,
      "frameBlock": "kubejs:void_frame_bricks",
      "isFluidIgniter": false,
      "itemIgniter": "kubejs:void_key",
      "dimension": "javd:void",
      "r": 100,
      "g": 12,
      "b": 140
    }
  ]
}